[
  {
    "_Type": "DataTable",
    "_Name": "ItemsClusterTable",
    "_Class": "UDataTable",
    "_Outer": "DeltaForce/Content/R13N/Common/Base/DataTables/ItemsClusterTable",
    "RowStruct": {
      "_Type": "UScriptClass",
      "_Name": "ItemsClusterRow",
      "_Class": "UScriptClass",
      "_Outer": null
    },
    "_Rows": {
      "\u5E78\u8FD0\u6728\u96D5": {
        "ClusterID": 100001,
        "ItemIdArray": [
          "15200000058"
        ],
        "RowDescription": "None"
      },
      "T1_\u91D1\u7EC4": {
        "ClusterID": 100002,
        "ItemIdArray": [
          "15060040001",
          "15080050090",
          "15030050006",
          "15060080014",
          "15080050101",
          "15070040001",
          "15030040003",
          "15080050015",
          "15080050002",
          "15030040013",
          "15060040003",
          "15080050009",
          "15040010019",
          "15080050115",
          "15080050129",
          "15080050137",
          "15080050140",
          "15080050162",
          "15080050163"
        ],
        "RowDescription": "None"
      },
      "T2_\u91D1\u7EC4": {
        "ClusterID": 100003,
        "ItemIdArray": [
          "15080050083",
          "15080050033",
          "15030050019",
          "15080050034",
          "15080050089",
          "15080050035",
          "15080050135",
          "15080050132",
          "15080050133",
          "15080050138",
          "15080050118",
          "15080050126",
          "15080050004",
          "15080050013"
        ],
        "RowDescription": "None"
      },
      "T3_\u91D1\u7EC4": {
        "ClusterID": 100004,
        "ItemIdArray": [
          "15080050082",
          "15020010036"
        ],
        "RowDescription": "None"
      },
      "T4_\u91D1\u7EC4": {
        "ClusterID": 100005,
        "ItemIdArray": [
          "15080050088",
          "15080050062"
        ],
        "RowDescription": "None"
      },
      "T1_1\u683C_\u5C0F\u7EA2\u7EC4": {
        "ClusterID": 100006,
        "ItemIdArray": [
          "15070050001",
          "15070040003",
          "15080050014",
          "15080050042",
          "15080050131"
        ],
        "RowDescription": "None"
      },
      "T1_30W_\u5C0F\u7EA2\u7EC4": {
        "ClusterID": 100007,
        "ItemIdArray": [
          "15030050018",
          "15080040001",
          "15060080015",
          "15030050001",
          "15080050010",
          "15060040004",
          "15010050001"
        ],
        "RowDescription": "None"
      },
      "T1_50W_\u5C0F\u7EA2\u7EC4": {
        "ClusterID": 100008,
        "ItemIdArray": [
          "15080050003",
          "15030010012",
          "15080050032",
          "15030050002"
        ],
        "RowDescription": "None"
      },
      "T2_\u7EA2\u7EC4": {
        "ClusterID": 100009,
        "ItemIdArray": [
          "15030050017",
          "15030050014",
          "15080050067",
          "15080050061",
          "15080050041",
          "15040050002",
          "15030050007",
          "15030050004",
          "15030050012",
          "15030050008",
          "15080050100",
          "15080050113",
          "15080050120",
          "15080050058"
        ],
        "RowDescription": "None"
      },
      "T3_\u7EA2\u7EC4": {
        "ClusterID": 100010,
        "ItemIdArray": [
          "15080050040",
          "15080050044",
          "15020010031",
          "15080050031",
          "15080050099",
          "15080050030",
          "15080050066",
          "15080050128",
          "15080050098"
        ],
        "RowDescription": "None"
      },
      "\u7279\u4EA7\u91D1\u7EC4": {
        "ClusterID": 100011,
        "ItemIdArray": [
          "15080050148",
          "15080050149",
          "15080050160",
          "15080050143",
          "15080050095",
          "15080050164",
          "15080050159",
          "15080050093",
          "15080050150",
          "15080050092",
          "15200000032",
          "15080050094",
          "15200000031",
          "15200000118",
          "15080050174",
          "15080050165",
          "15080050168",
          "15080050171",
          "15080050169"
        ],
        "RowDescription": "None"
      },
      "\u7279\u4EA7\u7EA2\u7EC4": {
        "ClusterID": 100012,
        "ItemIdArray": [
          "15080050161",
          "15080050151",
          "15030050013",
          "15080050122",
          "15020010033",
          "15080050144",
          "15080050123",
          "15080050121",
          "15080050167",
          "15080050170",
          "15080050166",
          "15080050173",
          "15080050175",
          "15200000060"
        ],
        "RowDescription": "None"
      },
      "\u9876\u7EA7\u7EA2_\u975E\u6D32\u4E4B\u5FC3": {
        "ClusterID": 100013,
        "ItemIdArray": [
          "15080050006"
        ],
        "RowDescription": "None"
      },
      "\u9876\u7EA7\u7EA2_\u590D\u82CF\u547C\u5438\u673A": {
        "ClusterID": 100014,
        "ItemIdArray": [
          "15080050097"
        ],
        "RowDescription": "None"
      },
      "\u9876\u7EA7\u7EA2_\u6D77\u6D0B\u4E4B\u6CEA": {
        "ClusterID": 100015,
        "ItemIdArray": [
          "15080050142"
        ],
        "RowDescription": "None"
      },
      "\u9274\u6743\u91D1\u7EC4": {
        "ClusterID": 100016,
        "ItemIdArray": [
          "15030050003",
          "15080050071",
          "15030040001",
          "15080050025",
          "15040010023",
          "15080050063"
        ],
        "RowDescription": "None"
      },
      "\u8054\u52A8\u91D1\u7EC4": {
        "ClusterID": 100017,
        "ItemIdArray": [
          "15200000070",
          "15200000075"
        ],
        "RowDescription": "None"
      },
      "\u8D5B\u5B63\u9650\u5B9A\u91D1\u7EC4": {
        "ClusterID": 100018,
        "ItemIdArray": [
          "15200000114",
          "15200000117"
        ],
        "RowDescription": "None"
      },
      "\u9274\u6743\u7EA2\u7EC4": {
        "ClusterID": 100019,
        "ItemIdArray": [
          "15080050069"
        ],
        "RowDescription": "None"
      },
      "\u8054\u52A8\u7EA2\u7EC4": {
        "ClusterID": 100020,
        "ItemIdArray": [
          "15200000071",
          "15200000072"
        ],
        "RowDescription": "None"
      },
      "\u8D5B\u5B63\u9650\u5B9A\u7EA2\u7EC4": {
        "ClusterID": 100021,
        "ItemIdArray": [
          "15200000125",
          "15200000115",
          "15200000124"
        ],
        "RowDescription": "None"
      },
      "1W\u7D2B\u7EC4": {
        "ClusterID": 100022,
        "ItemIdArray": [
          "15030040014",
          "15070050002",
          "15080050001",
          "15080050139",
          "15060080005",
          "15080040003",
          "15080050119",
          "15200000044",
          "15080050018",
          "15040010015",
          "15060080008",
          "15080040002",
          "15080050064",
          "15080050136",
          "15080050102",
          "15080050172"
        ],
        "RowDescription": "None"
      },
      "2.5W\u7D2B\u7EC4": {
        "ClusterID": 100023,
        "ItemIdArray": [
          "15080050106",
          "15030040012",
          "15080050114",
          "15080050016",
          "15030050005",
          "15030040006",
          "15080050091",
          "15030050011",
          "15040010014",
          "15080050103",
          "15030040005",
          "15080050124",
          "15020010024",
          "15060040002",
          "15080050068",
          "15080050038",
          "15080050045",
          "15030040007",
          "15080050105"
        ],
        "RowDescription": "None"
      },
      "5W\u7D2B\u7EC4": {
        "ClusterID": 100024,
        "ItemIdArray": [
          "15080050037",
          "15020050001",
          "15080050127",
          "15080050117",
          "15080050036",
          "15040040007",
          "15080050043",
          "15080050134"
        ],
        "RowDescription": "None"
      },
      "\u7279\u6B8A\u7D2B\u7EC4": {
        "ClusterID": 100025,
        "ItemIdArray": [
          "15080050156",
          "15080050155",
          "15080050158",
          "15080050157",
          "15080050057",
          "15020050005",
          "15020050003",
          "15040050003"
        ],
        "RowDescription": "None"
      },
      "She4\u5723\u8BDE\u7D2B\u8272\u7EC4": {
        "ClusterID": 100026,
        "ItemIdArray": [
          "15200000135"
        ],
        "RowDescription": "None"
      },
      "She4\u5723\u8BDE\u91D1\u8272\u7EC4": {
        "ClusterID": 100027,
        "ItemIdArray": [
          "15200000142"
        ],
        "RowDescription": "None"
      },
      "She4\u5723\u8BDE\u7EA2\u8272\u7EC4": {
        "ClusterID": 100028,
        "ItemIdArray": [
          "15200000143"
        ],
        "RowDescription": "None"
      },
      "Ma2\u8054\u52A8\u7EA2\u94A5\u5319": {
        "ClusterID": 100029,
        "ItemIdArray": [
          "15209600001"
        ],
        "RowDescription": "None"
      },
      "Ma2\u8054\u52A8\u91D1\u94A5\u5319\u9AD8\u500D": {
        "ClusterID": 100030,
        "ItemIdArray": [
          "15209600002",
          "15209600003",
          "15209600004"
        ],
        "RowDescription": "None"
      },
      "Ma2\u8054\u52A8\u7D2B\u94A5\u5319\u9AD8\u500D": {
        "ClusterID": 100031,
        "ItemIdArray": [
          "15209600005",
          "15209600006",
          "15209600007"
        ],
        "RowDescription": "None"
      },
      "Ma2\u8054\u52A8\u91D1\u94A5\u5319\u4F4E\u500D": {
        "ClusterID": 100032,
        "ItemIdArray": [
          "15209600002",
          "15209600003",
          "15209600004"
        ],
        "RowDescription": "None"
      },
      "Ma2\u8054\u52A8\u7D2B\u94A5\u5319\u4F4E\u500D": {
        "ClusterID": 100033,
        "ItemIdArray": [
          "15209600005",
          "15209600006",
          "15209600007"
        ],
        "RowDescription": "None"
      }
    },
    "_RowCount": 33
  }
]