[
  {
    "_Type": "DataTable",
    "_Name": "SlotCharing_CombinationTable",
    "_Class": "UDataTable",
    "_Outer": "DeltaForce/Content/DataTables/Ability/OperatorFormTool/CombinationTables/SlotCharing_CombinationTable",
    "RowStruct": {
      "_Type": "UScriptClass",
      "_Name": "SlotCharingDataRow",
      "_Class": "UScriptClass",
      "_Outer": null
    },
    "_Rows": {
      "\u533B\u7597\u7C89\u5C18": {
        "CdID": 88,
        "Slot": "ECharingSlot::ArmdedForceItem1",
        "WeaponSlot": 0,
        "SlotChargingData": [
          {
            "_StructType": "FStructFallback",
            "Init": 2,
            "Max": 2,
            "Time": 35,
            "UseTime": 0,
            "ChargeAmmoReplenish": 1,
            "PerkScaleMap": [],
            "MaxScoreReduceCDPercent": 0.25,
            "MaxScore": 0,
            "LimitPlayMode": [
              "EDFMGamePlayMode::GamePlayMode_SOL",
              "EDFMGamePlayMode::GamePlayMode_Raid",
              "EDFMGamePlayMode::GamePlayMode_IrisDiscovery",
              "EDFMGamePlayMode::GamePlayMode_SafeHouse",
              "EDFMGamePlayMode::GamePlayMode_Intro"
            ],
            "LimitPlaySubMode": [],
            "AddToCurrentAmmo": false,
            "CurrentAmmoNum": 0,
            "MaxClipAmmoNum": 0,
            "SkillNumType": "ESkillNumType::UT_Item",
            "DoneVoiceString": "",
            "NoCDType": false,
            "bWeaponCheckAmmo": false,
            "bUseLocalAmmo": false,
            "AmmoBoxChargeCnt": 0,
            "AmmoPackChargeCnt": 0,
            "SceneAmmoBoxChargeCnt": 0,
            "bOnlyWeaponCountAmmo": true,
            "bRebornReset": true,
            "bPauseCanAddScore": true,
            "InitialChargingPercent": 0,
            "bChargingOnlyWhenEmpty": false
          },
          {
            "_StructType": "FStructFallback",
            "Init": 2,
            "Max": 2,
            "Time": 25,
            "UseTime": 0,
            "ChargeAmmoReplenish": 1,
            "PerkScaleMap": [],
            "MaxScoreReduceCDPercent": 0.25,
            "MaxScore": 0,
            "LimitPlayMode": [
              "EDFMGamePlayMode::GamePlayMode_Conquest",
              "EDFMGamePlayMode::GamePlayMode_Breakthrough"
            ],
            "LimitPlaySubMode": [],
            "AddToCurrentAmmo": false,
            "CurrentAmmoNum": 0,
            "MaxClipAmmoNum": 0,
            "SkillNumType": "ESkillNumType::UT_Item",
            "DoneVoiceString": "",
            "NoCDType": false,
            "bWeaponCheckAmmo": false,
            "bUseLocalAmmo": false,
            "AmmoBoxChargeCnt": 0,
            "AmmoPackChargeCnt": 0,
            "SceneAmmoBoxChargeCnt": 0,
            "bOnlyWeaponCountAmmo": true,
            "bRebornReset": true,
            "bPauseCanAddScore": true,
            "InitialChargingPercent": 0,
            "bChargingOnlyWhenEmpty": false
          },
          {
            "_StructType": "FStructFallback",
            "Init": 2,
            "Max": 2,
            "Time": 35,
            "UseTime": 0,
            "ChargeAmmoReplenish": 1,
            "PerkScaleMap": [],
            "MaxScoreReduceCDPercent": 0.25,
            "MaxScore": 0,
            "LimitPlayMode": [
              "EDFMGamePlayMode::GamePlayMode_BombDefusal"
            ],
            "LimitPlaySubMode": [],
            "AddToCurrentAmmo": false,
            "CurrentAmmoNum": 0,
            "MaxClipAmmoNum": 0,
            "SkillNumType": "ESkillNumType::UT_Item",
            "DoneVoiceString": "",
            "NoCDType": false,
            "bWeaponCheckAmmo": false,
            "bUseLocalAmmo": false,
            "AmmoBoxChargeCnt": 0,
            "AmmoPackChargeCnt": 0,
            "SceneAmmoBoxChargeCnt": 0,
            "bOnlyWeaponCountAmmo": true,
            "bRebornReset": true,
            "bPauseCanAddScore": true,
            "InitialChargingPercent": 0,
            "bChargingOnlyWhenEmpty": false
          },
          {
            "_StructType": "FStructFallback",
            "Init": 2,
            "Max": 2,
            "Time": 35,
            "UseTime": 0,
            "ChargeAmmoReplenish": 1,
            "PerkScaleMap": [],
            "MaxScoreReduceCDPercent": 0.25,
            "MaxScore": 0,
            "LimitPlayMode": [
              "EDFMGamePlayMode::GamePlayMode_GoldenGunGun"
            ],
            "LimitPlaySubMode": [],
            "AddToCurrentAmmo": false,
            "CurrentAmmoNum": 0,
            "MaxClipAmmoNum": 0,
            "SkillNumType": "ESkillNumType::UT_Item",
            "DoneVoiceString": "",
            "NoCDType": false,
            "bWeaponCheckAmmo": false,
            "bUseLocalAmmo": false,
            "AmmoBoxChargeCnt": 0,
            "AmmoPackChargeCnt": 0,
            "SceneAmmoBoxChargeCnt": 0,
            "bOnlyWeaponCountAmmo": true,
            "bRebornReset": true,
            "bPauseCanAddScore": true,
            "InitialChargingPercent": 0,
            "bChargingOnlyWhenEmpty": false
          }
        ],
        "CheckSubMode": false,
        "RowDescription": "None"
      },
      "\u9065\u63A7\u70DF\u96FE": {
        "CdID": 89,
        "Slot": "ECharingSlot::ArmdedForceItem2",
        "WeaponSlot": 0,
        "SlotChargingData": [
          {
            "_StructType": "FStructFallback",
            "Init": 2,
            "Max": 2,
            "Time": 40,
            "UseTime": 0,
            "ChargeAmmoReplenish": 1,
            "PerkScaleMap": [],
            "MaxScoreReduceCDPercent": 0.25,
            "MaxScore": 0,
            "LimitPlayMode": [
              "EDFMGamePlayMode::GamePlayMode_SOL",
              "EDFMGamePlayMode::GamePlayMode_Raid"
            ],
            "LimitPlaySubMode": [],
            "AddToCurrentAmmo": false,
            "CurrentAmmoNum": 0,
            "MaxClipAmmoNum": 0,
            "SkillNumType": "ESkillNumType::UT_Item",
            "DoneVoiceString": "",
            "NoCDType": false,
            "bWeaponCheckAmmo": false,
            "bUseLocalAmmo": false,
            "AmmoBoxChargeCnt": 0,
            "AmmoPackChargeCnt": 0,
            "SceneAmmoBoxChargeCnt": 0,
            "bOnlyWeaponCountAmmo": true,
            "bRebornReset": true,
            "bPauseCanAddScore": true,
            "InitialChargingPercent": 0,
            "bChargingOnlyWhenEmpty": false
          },
          {
            "_StructType": "FStructFallback",
            "Init": 2,
            "Max": 2,
            "Time": 0,
            "UseTime": 0,
            "ChargeAmmoReplenish": 1,
            "PerkScaleMap": [],
            "MaxScoreReduceCDPercent": 0.25,
            "MaxScore": 0,
            "LimitPlayMode": [
              "EDFMGamePlayMode::GamePlayMode_Breakthrough",
              "EDFMGamePlayMode::GamePlayMode_Conquest"
            ],
            "LimitPlaySubMode": [],
            "AddToCurrentAmmo": false,
            "CurrentAmmoNum": 0,
            "MaxClipAmmoNum": 0,
            "SkillNumType": "ESkillNumType::UT_Item",
            "DoneVoiceString": "",
            "NoCDType": false,
            "bWeaponCheckAmmo": false,
            "bUseLocalAmmo": false,
            "AmmoBoxChargeCnt": 1,
            "AmmoPackChargeCnt": 1,
            "SceneAmmoBoxChargeCnt": 1,
            "bOnlyWeaponCountAmmo": true,
            "bRebornReset": true,
            "bPauseCanAddScore": true,
            "InitialChargingPercent": 0,
            "bChargingOnlyWhenEmpty": false
          },
          {
            "_StructType": "FStructFallback",
            "Init": 2,
            "Max": 2,
            "Time": 40,
            "UseTime": 0,
            "ChargeAmmoReplenish": 1,
            "PerkScaleMap": [],
            "MaxScoreReduceCDPercent": 0.25,
            "MaxScore": 0,
            "LimitPlayMode": [
              "EDFMGamePlayMode::GamePlayMode_BombDefusal"
            ],
            "LimitPlaySubMode": [],
            "AddToCurrentAmmo": false,
            "CurrentAmmoNum": 0,
            "MaxClipAmmoNum": 0,
            "SkillNumType": "ESkillNumType::UT_Item",
            "DoneVoiceString": "",
            "NoCDType": false,
            "bWeaponCheckAmmo": false,
            "bUseLocalAmmo": false,
            "AmmoBoxChargeCnt": 0,
            "AmmoPackChargeCnt": 0,
            "SceneAmmoBoxChargeCnt": 0,
            "bOnlyWeaponCountAmmo": true,
            "bRebornReset": true,
            "bPauseCanAddScore": true,
            "InitialChargingPercent": 0,
            "bChargingOnlyWhenEmpty": false
          },
          {
            "_StructType": "FStructFallback",
            "Init": 2,
            "Max": 2,
            "Time": 40,
            "UseTime": 0,
            "ChargeAmmoReplenish": 1,
            "PerkScaleMap": [],
            "MaxScoreReduceCDPercent": 0.25,
            "MaxScore": 0,
            "LimitPlayMode": [
              "EDFMGamePlayMode::GamePlayMode_GoldenGunGun"
            ],
            "LimitPlaySubMode": [],
            "AddToCurrentAmmo": false,
            "CurrentAmmoNum": 0,
            "MaxClipAmmoNum": 0,
            "SkillNumType": "ESkillNumType::UT_Item",
            "DoneVoiceString": "",
            "NoCDType": false,
            "bWeaponCheckAmmo": false,
            "bUseLocalAmmo": false,
            "AmmoBoxChargeCnt": 0,
            "AmmoPackChargeCnt": 0,
            "SceneAmmoBoxChargeCnt": 0,
            "bOnlyWeaponCountAmmo": true,
            "bRebornReset": true,
            "bPauseCanAddScore": true,
            "InitialChargingPercent": 0,
            "bChargingOnlyWhenEmpty": false
          }
        ],
        "CheckSubMode": false,
        "RowDescription": "None"
      },
      "\u6551\u63F4\u65E0\u4EBA\u673A": {
        "CdID": 90,
        "Slot": "ECharingSlot::Ability",
        "WeaponSlot": 0,
        "SlotChargingData": [
          {
            "_StructType": "FStructFallback",
            "Init": 0,
            "Max": 1,
            "Time": 120,
            "UseTime": 0,
            "ChargeAmmoReplenish": 1,
            "PerkScaleMap": [],
            "MaxScoreReduceCDPercent": 0.25,
            "MaxScore": 0,
            "LimitPlayMode": [
              "EDFMGamePlayMode::GamePlayMode_SOL",
              "EDFMGamePlayMode::GamePlayMode_Raid",
              "EDFMGamePlayMode::GamePlayMode_IrisDiscovery",
              "EDFMGamePlayMode::GamePlayMode_SafeHouse",
              "EDFMGamePlayMode::GamePlayMode_Intro"
            ],
            "LimitPlaySubMode": [],
            "AddToCurrentAmmo": false,
            "CurrentAmmoNum": 0,
            "MaxClipAmmoNum": 0,
            "SkillNumType": "ESkillNumType::UT_NoShow",
            "DoneVoiceString": "Skill_Ultimate_Charged",
            "NoCDType": false,
            "bWeaponCheckAmmo": false,
            "bUseLocalAmmo": false,
            "AmmoBoxChargeCnt": 0,
            "AmmoPackChargeCnt": 0,
            "SceneAmmoBoxChargeCnt": 0,
            "bOnlyWeaponCountAmmo": true,
            "bRebornReset": false,
            "bPauseCanAddScore": true,
            "InitialChargingPercent": 0,
            "bChargingOnlyWhenEmpty": false
          },
          {
            "_StructType": "FStructFallback",
            "Init": 0,
            "Max": 1,
            "Time": 90,
            "UseTime": 0,
            "ChargeAmmoReplenish": 1,
            "PerkScaleMap": [],
            "MaxScoreReduceCDPercent": 0.25,
            "MaxScore": 13500,
            "LimitPlayMode": [
              "EDFMGamePlayMode::GamePlayMode_Breakthrough"
            ],
            "LimitPlaySubMode": [],
            "AddToCurrentAmmo": false,
            "CurrentAmmoNum": 0,
            "MaxClipAmmoNum": 0,
            "SkillNumType": "ESkillNumType::UT_NoShow",
            "DoneVoiceString": "",
            "NoCDType": false,
            "bWeaponCheckAmmo": false,
            "bUseLocalAmmo": false,
            "AmmoBoxChargeCnt": 0,
            "AmmoPackChargeCnt": 0,
            "SceneAmmoBoxChargeCnt": 0,
            "bOnlyWeaponCountAmmo": true,
            "bRebornReset": false,
            "bPauseCanAddScore": true,
            "InitialChargingPercent": 0,
            "bChargingOnlyWhenEmpty": false
          },
          {
            "_StructType": "FStructFallback",
            "Init": 0,
            "Max": 1,
            "Time": 60,
            "UseTime": 0,
            "ChargeAmmoReplenish": 1,
            "PerkScaleMap": [],
            "MaxScoreReduceCDPercent": 0.25,
            "MaxScore": 13500,
            "LimitPlayMode": [
              "EDFMGamePlayMode::GamePlayMode_Conquest"
            ],
            "LimitPlaySubMode": [],
            "AddToCurrentAmmo": false,
            "CurrentAmmoNum": 0,
            "MaxClipAmmoNum": 0,
            "SkillNumType": "ESkillNumType::UT_NoShow",
            "DoneVoiceString": "",
            "NoCDType": false,
            "bWeaponCheckAmmo": false,
            "bUseLocalAmmo": false,
            "AmmoBoxChargeCnt": 0,
            "AmmoPackChargeCnt": 0,
            "SceneAmmoBoxChargeCnt": 0,
            "bOnlyWeaponCountAmmo": true,
            "bRebornReset": false,
            "bPauseCanAddScore": true,
            "InitialChargingPercent": 0,
            "bChargingOnlyWhenEmpty": false
          },
          {
            "_StructType": "FStructFallback",
            "Init": 0,
            "Max": 1,
            "Time": 60,
            "UseTime": 0,
            "ChargeAmmoReplenish": 1,
            "PerkScaleMap": [],
            "MaxScoreReduceCDPercent": 0.25,
            "MaxScore": 0,
            "LimitPlayMode": [],
            "LimitPlaySubMode": [
              "EDFMGamePlaySubMode::GamePlaySubMode_Arena"
            ],
            "AddToCurrentAmmo": false,
            "CurrentAmmoNum": 0,
            "MaxClipAmmoNum": 0,
            "SkillNumType": "ESkillNumType::UT_NoShow",
            "DoneVoiceString": "Skill_Ultimate_Charged",
            "NoCDType": false,
            "bWeaponCheckAmmo": false,
            "bUseLocalAmmo": false,
            "AmmoBoxChargeCnt": 0,
            "AmmoPackChargeCnt": 0,
            "SceneAmmoBoxChargeCnt": 0,
            "bOnlyWeaponCountAmmo": true,
            "bRebornReset": true,
            "bPauseCanAddScore": true,
            "InitialChargingPercent": 0,
            "bChargingOnlyWhenEmpty": false
          },
          {
            "_StructType": "FStructFallback",
            "Init": 0,
            "Max": 1,
            "Time": 70,
            "UseTime": 0,
            "ChargeAmmoReplenish": 1,
            "PerkScaleMap": [],
            "MaxScoreReduceCDPercent": 0.25,
            "MaxScore": 13500,
            "LimitPlayMode": [],
            "LimitPlaySubMode": [
              "EDFMGamePlaySubMode::GamePlaySubMode_TacticalConquest",
              "EDFMGamePlaySubMode::GamePlaySubMode_CaptureFlag"
            ],
            "AddToCurrentAmmo": false,
            "CurrentAmmoNum": 0,
            "MaxClipAmmoNum": 0,
            "SkillNumType": "ESkillNumType::UT_NoShow",
            "DoneVoiceString": "",
            "NoCDType": false,
            "bWeaponCheckAmmo": false,
            "bUseLocalAmmo": false,
            "AmmoBoxChargeCnt": 0,
            "AmmoPackChargeCnt": 0,
            "SceneAmmoBoxChargeCnt": 0,
            "bOnlyWeaponCountAmmo": true,
            "bRebornReset": false,
            "bPauseCanAddScore": true,
            "InitialChargingPercent": 0,
            "bChargingOnlyWhenEmpty": false
          },
          {
            "_StructType": "FStructFallback",
            "Init": 0,
            "Max": 1,
            "Time": 120,
            "UseTime": 0,
            "ChargeAmmoReplenish": 1,
            "PerkScaleMap": [],
            "MaxScoreReduceCDPercent": 0.25,
            "MaxScore": 0,
            "LimitPlayMode": [
              "EDFMGamePlayMode::GamePlayMode_BombDefusal"
            ],
            "LimitPlaySubMode": [],
            "AddToCurrentAmmo": false,
            "CurrentAmmoNum": 0,
            "MaxClipAmmoNum": 0,
            "SkillNumType": "ESkillNumType::UT_NoShow",
            "DoneVoiceString": "Skill_Ultimate_Charged",
            "NoCDType": false,
            "bWeaponCheckAmmo": false,
            "bUseLocalAmmo": false,
            "AmmoBoxChargeCnt": 0,
            "AmmoPackChargeCnt": 0,
            "SceneAmmoBoxChargeCnt": 0,
            "bOnlyWeaponCountAmmo": true,
            "bRebornReset": false,
            "bPauseCanAddScore": true,
            "InitialChargingPercent": 0,
            "bChargingOnlyWhenEmpty": false
          },
          {
            "_StructType": "FStructFallback",
            "Init": 0,
            "Max": 1,
            "Time": 120,
            "UseTime": 0,
            "ChargeAmmoReplenish": 1,
            "PerkScaleMap": [],
            "MaxScoreReduceCDPercent": 0.25,
            "MaxScore": 0,
            "LimitPlayMode": [
              "EDFMGamePlayMode::GamePlayMode_GoldenGunGun"
            ],
            "LimitPlaySubMode": [],
            "AddToCurrentAmmo": false,
            "CurrentAmmoNum": 0,
            "MaxClipAmmoNum": 0,
            "SkillNumType": "ESkillNumType::UT_NoShow",
            "DoneVoiceString": "Skill_Ultimate_Charged",
            "NoCDType": false,
            "bWeaponCheckAmmo": false,
            "bUseLocalAmmo": false,
            "AmmoBoxChargeCnt": 0,
            "AmmoPackChargeCnt": 0,
            "SceneAmmoBoxChargeCnt": 0,
            "bOnlyWeaponCountAmmo": true,
            "bRebornReset": false,
            "bPauseCanAddScore": true,
            "InitialChargingPercent": 0,
            "bChargingOnlyWhenEmpty": false
          }
        ],
        "CheckSubMode": true,
        "RowDescription": "None"
      },
      "95": {
        "CdID": 95,
        "Slot": "ECharingSlot::Ability",
        "WeaponSlot": 0,
        "SlotChargingData": [
          {
            "_StructType": "FStructFallback",
            "Init": 0,
            "Max": 1,
            "Time": 120,
            "UseTime": 0,
            "ChargeAmmoReplenish": 1,
            "PerkScaleMap": [],
            "MaxScoreReduceCDPercent": 0.25,
            "MaxScore": 0,
            "LimitPlayMode": [
              "EDFMGamePlayMode::GamePlayMode_SOL",
              "EDFMGamePlayMode::GamePlayMode_Raid",
              "EDFMGamePlayMode::GamePlayMode_Intro",
              "EDFMGamePlayMode::GamePlayMode_SafeHouse",
              "EDFMGamePlayMode::GamePlayMode_IrisDiscovery"
            ],
            "LimitPlaySubMode": [],
            "AddToCurrentAmmo": true,
            "CurrentAmmoNum": 0,
            "MaxClipAmmoNum": 1,
            "SkillNumType": "ESkillNumType::UT_NoShow",
            "DoneVoiceString": "Skill_Ultimate_Charged",
            "NoCDType": false,
            "bWeaponCheckAmmo": false,
            "bUseLocalAmmo": false,
            "AmmoBoxChargeCnt": 0,
            "AmmoPackChargeCnt": 0,
            "SceneAmmoBoxChargeCnt": 0,
            "bOnlyWeaponCountAmmo": true,
            "bRebornReset": false,
            "bPauseCanAddScore": true,
            "InitialChargingPercent": 0,
            "bChargingOnlyWhenEmpty": false
          },
          {
            "_StructType": "FStructFallback",
            "Init": 0,
            "Max": 1,
            "Time": 90,
            "UseTime": 0,
            "ChargeAmmoReplenish": 1,
            "PerkScaleMap": [],
            "MaxScoreReduceCDPercent": 0.25,
            "MaxScore": 13500,
            "LimitPlayMode": [
              "EDFMGamePlayMode::GamePlayMode_Breakthrough",
              "EDFMGamePlayMode::GamePlayMode_Conquest"
            ],
            "LimitPlaySubMode": [],
            "AddToCurrentAmmo": true,
            "CurrentAmmoNum": 0,
            "MaxClipAmmoNum": 1,
            "SkillNumType": "ESkillNumType::UT_NoShow",
            "DoneVoiceString": "",
            "NoCDType": false,
            "bWeaponCheckAmmo": false,
            "bUseLocalAmmo": false,
            "AmmoBoxChargeCnt": 0,
            "AmmoPackChargeCnt": 0,
            "SceneAmmoBoxChargeCnt": 0,
            "bOnlyWeaponCountAmmo": true,
            "bRebornReset": false,
            "bPauseCanAddScore": true,
            "InitialChargingPercent": 0,
            "bChargingOnlyWhenEmpty": false
          },
          {
            "_StructType": "FStructFallback",
            "Init": 0,
            "Max": 1,
            "Time": 90,
            "UseTime": 0,
            "ChargeAmmoReplenish": 1,
            "PerkScaleMap": [],
            "MaxScoreReduceCDPercent": 0.25,
            "MaxScore": 0,
            "LimitPlayMode": [],
            "LimitPlaySubMode": [
              "EDFMGamePlaySubMode::GamePlaySubMode_Arena"
            ],
            "AddToCurrentAmmo": true,
            "CurrentAmmoNum": 0,
            "MaxClipAmmoNum": 1,
            "SkillNumType": "ESkillNumType::UT_NoShow",
            "DoneVoiceString": "Skill_Ultimate_Charged",
            "NoCDType": false,
            "bWeaponCheckAmmo": false,
            "bUseLocalAmmo": false,
            "AmmoBoxChargeCnt": 0,
            "AmmoPackChargeCnt": 0,
            "SceneAmmoBoxChargeCnt": 0,
            "bOnlyWeaponCountAmmo": true,
            "bRebornReset": true,
            "bPauseCanAddScore": true,
            "InitialChargingPercent": 0,
            "bChargingOnlyWhenEmpty": false
          },
          {
            "_StructType": "FStructFallback",
            "Init": 0,
            "Max": 1,
            "Time": 90,
            "UseTime": 0,
            "ChargeAmmoReplenish": 1,
            "PerkScaleMap": [],
            "MaxScoreReduceCDPercent": 0.25,
            "MaxScore": 13500,
            "LimitPlayMode": [
              "EDFMGamePlayMode::GamePlayMode_BombDefusal"
            ],
            "LimitPlaySubMode": [],
            "AddToCurrentAmmo": true,
            "CurrentAmmoNum": 0,
            "MaxClipAmmoNum": 1,
            "SkillNumType": "ESkillNumType::UT_NoShow",
            "DoneVoiceString": "",
            "NoCDType": false,
            "bWeaponCheckAmmo": false,
            "bUseLocalAmmo": false,
            "AmmoBoxChargeCnt": 0,
            "AmmoPackChargeCnt": 0,
            "SceneAmmoBoxChargeCnt": 0,
            "bOnlyWeaponCountAmmo": true,
            "bRebornReset": false,
            "bPauseCanAddScore": true,
            "InitialChargingPercent": 0,
            "bChargingOnlyWhenEmpty": false
          },
          {
            "_StructType": "FStructFallback",
            "Init": 0,
            "Max": 1,
            "Time": 90,
            "UseTime": 0,
            "ChargeAmmoReplenish": 1,
            "PerkScaleMap": [],
            "MaxScoreReduceCDPercent": 0.25,
            "MaxScore": 13500,
            "LimitPlayMode": [
              "EDFMGamePlayMode::GamePlayMode_GoldenGunGun"
            ],
            "LimitPlaySubMode": [],
            "AddToCurrentAmmo": true,
            "CurrentAmmoNum": 0,
            "MaxClipAmmoNum": 1,
            "SkillNumType": "ESkillNumType::UT_NoShow",
            "DoneVoiceString": "",
            "NoCDType": false,
            "bWeaponCheckAmmo": false,
            "bUseLocalAmmo": false,
            "AmmoBoxChargeCnt": 0,
            "AmmoPackChargeCnt": 0,
            "SceneAmmoBoxChargeCnt": 0,
            "bOnlyWeaponCountAmmo": true,
            "bRebornReset": false,
            "bPauseCanAddScore": true,
            "InitialChargingPercent": 0,
            "bChargingOnlyWhenEmpty": false
          }
        ],
        "CheckSubMode": true,
        "RowDescription": "None"
      },
      "96": {
        "CdID": 96,
        "Slot": "ECharingSlot::ArmdedForceItem1",
        "WeaponSlot": 136,
        "SlotChargingData": [
          {
            "_StructType": "FStructFallback",
            "Init": 0,
            "Max": 1,
            "Time": 30,
            "UseTime": 0,
            "ChargeAmmoReplenish": 1,
            "PerkScaleMap": [],
            "MaxScoreReduceCDPercent": 0.25,
            "MaxScore": 0,
            "LimitPlayMode": [
              "EDFMGamePlayMode::GamePlayMode_Breakthrough",
              "EDFMGamePlayMode::GamePlayMode_Conquest"
            ],
            "LimitPlaySubMode": [],
            "AddToCurrentAmmo": true,
            "CurrentAmmoNum": 1,
            "MaxClipAmmoNum": 1,
            "SkillNumType": "ESkillNumType::UT_Item",
            "DoneVoiceString": "",
            "NoCDType": false,
            "bWeaponCheckAmmo": false,
            "bUseLocalAmmo": false,
            "AmmoBoxChargeCnt": 0,
            "AmmoPackChargeCnt": 0,
            "SceneAmmoBoxChargeCnt": 0,
            "bOnlyWeaponCountAmmo": true,
            "bRebornReset": true,
            "bPauseCanAddScore": true,
            "InitialChargingPercent": 0,
            "bChargingOnlyWhenEmpty": false
          },
          {
            "_StructType": "FStructFallback",
            "Init": 1,
            "Max": 1,
            "Time": 40,
            "UseTime": 0,
            "ChargeAmmoReplenish": 1,
            "PerkScaleMap": [],
            "MaxScoreReduceCDPercent": 0.25,
            "MaxScore": 0,
            "LimitPlayMode": [
              "EDFMGamePlayMode::GamePlayMode_SOL",
              "EDFMGamePlayMode::GamePlayMode_Raid",
              "EDFMGamePlayMode::GamePlayMode_IrisDiscovery",
              "EDFMGamePlayMode::GamePlayMode_SafeHouse",
              "EDFMGamePlayMode::GamePlayMode_Intro"
            ],
            "LimitPlaySubMode": [],
            "AddToCurrentAmmo": true,
            "CurrentAmmoNum": 1,
            "MaxClipAmmoNum": 1,
            "SkillNumType": "ESkillNumType::UT_Item",
            "DoneVoiceString": "",
            "NoCDType": false,
            "bWeaponCheckAmmo": false,
            "bUseLocalAmmo": false,
            "AmmoBoxChargeCnt": 0,
            "AmmoPackChargeCnt": 0,
            "SceneAmmoBoxChargeCnt": 0,
            "bOnlyWeaponCountAmmo": true,
            "bRebornReset": true,
            "bPauseCanAddScore": true,
            "InitialChargingPercent": 0,
            "bChargingOnlyWhenEmpty": false
          },
          {
            "_StructType": "FStructFallback",
            "Init": 0,
            "Max": 1,
            "Time": 30,
            "UseTime": 0,
            "ChargeAmmoReplenish": 1,
            "PerkScaleMap": [],
            "MaxScoreReduceCDPercent": 0.25,
            "MaxScore": 0,
            "LimitPlayMode": [],
            "LimitPlaySubMode": [
              "EDFMGamePlaySubMode::GamePlaySubMode_Arena"
            ],
            "AddToCurrentAmmo": true,
            "CurrentAmmoNum": 1,
            "MaxClipAmmoNum": 1,
            "SkillNumType": "ESkillNumType::UT_Item",
            "DoneVoiceString": "",
            "NoCDType": false,
            "bWeaponCheckAmmo": false,
            "bUseLocalAmmo": false,
            "AmmoBoxChargeCnt": 0,
            "AmmoPackChargeCnt": 0,
            "SceneAmmoBoxChargeCnt": 0,
            "bOnlyWeaponCountAmmo": true,
            "bRebornReset": true,
            "bPauseCanAddScore": true,
            "InitialChargingPercent": 0,
            "bChargingOnlyWhenEmpty": false
          },
          {
            "_StructType": "FStructFallback",
            "Init": 0,
            "Max": 1,
            "Time": 30,
            "UseTime": 0,
            "ChargeAmmoReplenish": 1,
            "PerkScaleMap": [],
            "MaxScoreReduceCDPercent": 0.25,
            "MaxScore": 0,
            "LimitPlayMode": [
              "EDFMGamePlayMode::GamePlayMode_BombDefusal"
            ],
            "LimitPlaySubMode": [],
            "AddToCurrentAmmo": true,
            "CurrentAmmoNum": 1,
            "MaxClipAmmoNum": 1,
            "SkillNumType": "ESkillNumType::UT_Item",
            "DoneVoiceString": "",
            "NoCDType": false,
            "bWeaponCheckAmmo": false,
            "bUseLocalAmmo": false,
            "AmmoBoxChargeCnt": 0,
            "AmmoPackChargeCnt": 0,
            "SceneAmmoBoxChargeCnt": 0,
            "bOnlyWeaponCountAmmo": true,
            "bRebornReset": true,
            "bPauseCanAddScore": true,
            "InitialChargingPercent": 0,
            "bChargingOnlyWhenEmpty": false
          },
          {
            "_StructType": "FStructFallback",
            "Init": 0,
            "Max": 1,
            "Time": 30,
            "UseTime": 0,
            "ChargeAmmoReplenish": 1,
            "PerkScaleMap": [],
            "MaxScoreReduceCDPercent": 0.25,
            "MaxScore": 0,
            "LimitPlayMode": [
              "EDFMGamePlayMode::GamePlayMode_GoldenGunGun"
            ],
            "LimitPlaySubMode": [],
            "AddToCurrentAmmo": true,
            "CurrentAmmoNum": 1,
            "MaxClipAmmoNum": 1,
            "SkillNumType": "ESkillNumType::UT_Item",
            "DoneVoiceString": "",
            "NoCDType": false,
            "bWeaponCheckAmmo": false,
            "bUseLocalAmmo": false,
            "AmmoBoxChargeCnt": 0,
            "AmmoPackChargeCnt": 0,
            "SceneAmmoBoxChargeCnt": 0,
            "bOnlyWeaponCountAmmo": true,
            "bRebornReset": true,
            "bPauseCanAddScore": true,
            "InitialChargingPercent": 0,
            "bChargingOnlyWhenEmpty": false
          }
        ],
        "CheckSubMode": false,
        "RowDescription": "None"
      },
      "97": {
        "CdID": 97,
        "Slot": "ECharingSlot::ArmdedForceItem2",
        "WeaponSlot": 0,
        "SlotChargingData": [
          {
            "_StructType": "FStructFallback",
            "Init": 1,
            "Max": 1,
            "Time": 55,
            "UseTime": 0,
            "ChargeAmmoReplenish": 1,
            "PerkScaleMap": [],
            "MaxScoreReduceCDPercent": 0.25,
            "MaxScore": 0,
            "LimitPlayMode": [
              "EDFMGamePlayMode::GamePlayMode_SOL",
              "EDFMGamePlayMode::GamePlayMode_Raid",
              "EDFMGamePlayMode::GamePlayMode_Intro"
            ],
            "LimitPlaySubMode": [],
            "AddToCurrentAmmo": false,
            "CurrentAmmoNum": 0,
            "MaxClipAmmoNum": 0,
            "SkillNumType": "ESkillNumType::UT_Item",
            "DoneVoiceString": "",
            "NoCDType": false,
            "bWeaponCheckAmmo": false,
            "bUseLocalAmmo": false,
            "AmmoBoxChargeCnt": 0,
            "AmmoPackChargeCnt": 0,
            "SceneAmmoBoxChargeCnt": 0,
            "bOnlyWeaponCountAmmo": true,
            "bRebornReset": true,
            "bPauseCanAddScore": true,
            "InitialChargingPercent": 0,
            "bChargingOnlyWhenEmpty": false
          },
          {
            "_StructType": "FStructFallback",
            "Init": 1,
            "Max": 2,
            "Time": 0,
            "UseTime": 0,
            "ChargeAmmoReplenish": 1,
            "PerkScaleMap": [],
            "MaxScoreReduceCDPercent": 0.25,
            "MaxScore": 0,
            "LimitPlayMode": [
              "EDFMGamePlayMode::GamePlayMode_Breakthrough",
              "EDFMGamePlayMode::GamePlayMode_Conquest"
            ],
            "LimitPlaySubMode": [],
            "AddToCurrentAmmo": false,
            "CurrentAmmoNum": 0,
            "MaxClipAmmoNum": 0,
            "SkillNumType": "ESkillNumType::UT_Item",
            "DoneVoiceString": "",
            "NoCDType": false,
            "bWeaponCheckAmmo": false,
            "bUseLocalAmmo": false,
            "AmmoBoxChargeCnt": 1,
            "AmmoPackChargeCnt": 1,
            "SceneAmmoBoxChargeCnt": 1,
            "bOnlyWeaponCountAmmo": true,
            "bRebornReset": true,
            "bPauseCanAddScore": true,
            "InitialChargingPercent": 0,
            "bChargingOnlyWhenEmpty": false
          },
          {
            "_StructType": "FStructFallback",
            "Init": 1,
            "Max": 1,
            "Time": 55,
            "UseTime": 0,
            "ChargeAmmoReplenish": 1,
            "PerkScaleMap": [],
            "MaxScoreReduceCDPercent": 0.25,
            "MaxScore": 0,
            "LimitPlayMode": [],
            "LimitPlaySubMode": [
              "EDFMGamePlaySubMode::GamePlaySubMode_Arena"
            ],
            "AddToCurrentAmmo": false,
            "CurrentAmmoNum": 0,
            "MaxClipAmmoNum": 0,
            "SkillNumType": "ESkillNumType::UT_Item",
            "DoneVoiceString": "",
            "NoCDType": false,
            "bWeaponCheckAmmo": false,
            "bUseLocalAmmo": false,
            "AmmoBoxChargeCnt": 0,
            "AmmoPackChargeCnt": 0,
            "SceneAmmoBoxChargeCnt": 0,
            "bOnlyWeaponCountAmmo": true,
            "bRebornReset": true,
            "bPauseCanAddScore": true,
            "InitialChargingPercent": 0,
            "bChargingOnlyWhenEmpty": false
          },
          {
            "_StructType": "FStructFallback",
            "Init": 1,
            "Max": 1,
            "Time": 55,
            "UseTime": 0,
            "ChargeAmmoReplenish": 1,
            "PerkScaleMap": [],
            "MaxScoreReduceCDPercent": 0.25,
            "MaxScore": 0,
            "LimitPlayMode": [
              "EDFMGamePlayMode::GamePlayMode_BombDefusal"
            ],
            "LimitPlaySubMode": [],
            "AddToCurrentAmmo": false,
            "CurrentAmmoNum": 0,
            "MaxClipAmmoNum": 0,
            "SkillNumType": "ESkillNumType::UT_Item",
            "DoneVoiceString": "",
            "NoCDType": false,
            "bWeaponCheckAmmo": false,
            "bUseLocalAmmo": false,
            "AmmoBoxChargeCnt": 0,
            "AmmoPackChargeCnt": 0,
            "SceneAmmoBoxChargeCnt": 0,
            "bOnlyWeaponCountAmmo": true,
            "bRebornReset": true,
            "bPauseCanAddScore": true,
            "InitialChargingPercent": 0,
            "bChargingOnlyWhenEmpty": false
          },
          {
            "_StructType": "FStructFallback",
            "Init": 1,
            "Max": 1,
            "Time": 55,
            "UseTime": 0,
            "ChargeAmmoReplenish": 1,
            "PerkScaleMap": [],
            "MaxScoreReduceCDPercent": 0.25,
            "MaxScore": 0,
            "LimitPlayMode": [
              "EDFMGamePlayMode::GamePlayMode_GoldenGunGun"
            ],
            "LimitPlaySubMode": [],
            "AddToCurrentAmmo": false,
            "CurrentAmmoNum": 0,
            "MaxClipAmmoNum": 0,
            "SkillNumType": "ESkillNumType::UT_Item",
            "DoneVoiceString": "",
            "NoCDType": false,
            "bWeaponCheckAmmo": false,
            "bUseLocalAmmo": false,
            "AmmoBoxChargeCnt": 0,
            "AmmoPackChargeCnt": 0,
            "SceneAmmoBoxChargeCnt": 0,
            "bOnlyWeaponCountAmmo": true,
            "bRebornReset": true,
            "bPauseCanAddScore": true,
            "InitialChargingPercent": 0,
            "bChargingOnlyWhenEmpty": false
          }
        ],
        "CheckSubMode": false,
        "RowDescription": "None"
      },
      "\u6295\u63B7\u578B\u5E72\u6270\u88C5\u7F6E": {
        "CdID": 93,
        "Slot": "ECharingSlot::ArmdedForceItem1",
        "WeaponSlot": 0,
        "SlotChargingData": [
          {
            "_StructType": "FStructFallback",
            "Init": 2,
            "Max": 2,
            "Time": 35,
            "UseTime": 0,
            "ChargeAmmoReplenish": 1,
            "PerkScaleMap": [],
            "MaxScoreReduceCDPercent": 0.25,
            "MaxScore": 0,
            "LimitPlayMode": [
              "EDFMGamePlayMode::GamePlayMode_SOL",
              "EDFMGamePlayMode::GamePlayMode_Raid",
              "EDFMGamePlayMode::GamePlayMode_IrisDiscovery",
              "EDFMGamePlayMode::GamePlayMode_SafeHouse",
              "EDFMGamePlayMode::GamePlayMode_Intro"
            ],
            "LimitPlaySubMode": [],
            "AddToCurrentAmmo": true,
            "CurrentAmmoNum": 0,
            "MaxClipAmmoNum": 0,
            "SkillNumType": "ESkillNumType::UT_Item",
            "DoneVoiceString": "",
            "NoCDType": false,
            "bWeaponCheckAmmo": true,
            "bUseLocalAmmo": true,
            "AmmoBoxChargeCnt": 0,
            "AmmoPackChargeCnt": 0,
            "SceneAmmoBoxChargeCnt": 0,
            "bOnlyWeaponCountAmmo": true,
            "bRebornReset": true,
            "bPauseCanAddScore": true,
            "InitialChargingPercent": 0,
            "bChargingOnlyWhenEmpty": false
          },
          {
            "_StructType": "FStructFallback",
            "Init": 2,
            "Max": 2,
            "Time": 35,
            "UseTime": 0,
            "ChargeAmmoReplenish": 1,
            "PerkScaleMap": [],
            "MaxScoreReduceCDPercent": 0.25,
            "MaxScore": 2000,
            "LimitPlayMode": [
              "EDFMGamePlayMode::GamePlayMode_Conquest",
              "EDFMGamePlayMode::GamePlayMode_Breakthrough"
            ],
            "LimitPlaySubMode": [],
            "AddToCurrentAmmo": true,
            "CurrentAmmoNum": 0,
            "MaxClipAmmoNum": 0,
            "SkillNumType": "ESkillNumType::UT_Item",
            "DoneVoiceString": "",
            "NoCDType": false,
            "bWeaponCheckAmmo": true,
            "bUseLocalAmmo": true,
            "AmmoBoxChargeCnt": 0,
            "AmmoPackChargeCnt": 0,
            "SceneAmmoBoxChargeCnt": 0,
            "bOnlyWeaponCountAmmo": true,
            "bRebornReset": true,
            "bPauseCanAddScore": true,
            "InitialChargingPercent": 0,
            "bChargingOnlyWhenEmpty": false
          },
          {
            "_StructType": "FStructFallback",
            "Init": 2,
            "Max": 2,
            "Time": 35,
            "UseTime": 0,
            "ChargeAmmoReplenish": 1,
            "PerkScaleMap": [],
            "MaxScoreReduceCDPercent": 0.25,
            "MaxScore": 0,
            "LimitPlayMode": [
              "EDFMGamePlayMode::GamePlayMode_BombDefusal"
            ],
            "LimitPlaySubMode": [],
            "AddToCurrentAmmo": true,
            "CurrentAmmoNum": 0,
            "MaxClipAmmoNum": 0,
            "SkillNumType": "ESkillNumType::UT_Item",
            "DoneVoiceString": "",
            "NoCDType": false,
            "bWeaponCheckAmmo": true,
            "bUseLocalAmmo": true,
            "AmmoBoxChargeCnt": 0,
            "AmmoPackChargeCnt": 0,
            "SceneAmmoBoxChargeCnt": 0,
            "bOnlyWeaponCountAmmo": true,
            "bRebornReset": true,
            "bPauseCanAddScore": true,
            "InitialChargingPercent": 0,
            "bChargingOnlyWhenEmpty": false
          },
          {
            "_StructType": "FStructFallback",
            "Init": 2,
            "Max": 2,
            "Time": 35,
            "UseTime": 0,
            "ChargeAmmoReplenish": 1,
            "PerkScaleMap": [],
            "MaxScoreReduceCDPercent": 0.25,
            "MaxScore": 0,
            "LimitPlayMode": [
              "EDFMGamePlayMode::GamePlayMode_GoldenGunGun"
            ],
            "LimitPlaySubMode": [],
            "AddToCurrentAmmo": true,
            "CurrentAmmoNum": 0,
            "MaxClipAmmoNum": 0,
            "SkillNumType": "ESkillNumType::UT_Item",
            "DoneVoiceString": "",
            "NoCDType": false,
            "bWeaponCheckAmmo": true,
            "bUseLocalAmmo": true,
            "AmmoBoxChargeCnt": 0,
            "AmmoPackChargeCnt": 0,
            "SceneAmmoBoxChargeCnt": 0,
            "bOnlyWeaponCountAmmo": true,
            "bRebornReset": true,
            "bPauseCanAddScore": true,
            "InitialChargingPercent": 0,
            "bChargingOnlyWhenEmpty": false
          }
        ],
        "CheckSubMode": false,
        "RowDescription": "None"
      },
      "\u5EF6\u8FDF\u95EA\u5149\u5F39": {
        "CdID": 94,
        "Slot": "ECharingSlot::ArmdedForceItem2",
        "WeaponSlot": 0,
        "SlotChargingData": [
          {
            "_StructType": "FStructFallback",
            "Init": 2,
            "Max": 2,
            "Time": 45,
            "UseTime": 0,
            "ChargeAmmoReplenish": 1,
            "PerkScaleMap": [],
            "MaxScoreReduceCDPercent": 0.25,
            "MaxScore": 0,
            "LimitPlayMode": [
              "EDFMGamePlayMode::GamePlayMode_SOL",
              "EDFMGamePlayMode::GamePlayMode_Raid"
            ],
            "LimitPlaySubMode": [],
            "AddToCurrentAmmo": false,
            "CurrentAmmoNum": 0,
            "MaxClipAmmoNum": 0,
            "SkillNumType": "ESkillNumType::UT_Item",
            "DoneVoiceString": "",
            "NoCDType": false,
            "bWeaponCheckAmmo": false,
            "bUseLocalAmmo": false,
            "AmmoBoxChargeCnt": 0,
            "AmmoPackChargeCnt": 0,
            "SceneAmmoBoxChargeCnt": 0,
            "bOnlyWeaponCountAmmo": true,
            "bRebornReset": true,
            "bPauseCanAddScore": true,
            "InitialChargingPercent": 0,
            "bChargingOnlyWhenEmpty": false
          },
          {
            "_StructType": "FStructFallback",
            "Init": 2,
            "Max": 2,
            "Time": 45,
            "UseTime": 0,
            "ChargeAmmoReplenish": 1,
            "PerkScaleMap": [],
            "MaxScoreReduceCDPercent": 0.25,
            "MaxScore": 0,
            "LimitPlayMode": [
              "EDFMGamePlayMode::GamePlayMode_Breakthrough",
              "EDFMGamePlayMode::GamePlayMode_Conquest"
            ],
            "LimitPlaySubMode": [],
            "AddToCurrentAmmo": false,
            "CurrentAmmoNum": 0,
            "MaxClipAmmoNum": 0,
            "SkillNumType": "ESkillNumType::UT_Item",
            "DoneVoiceString": "",
            "NoCDType": false,
            "bWeaponCheckAmmo": false,
            "bUseLocalAmmo": false,
            "AmmoBoxChargeCnt": 1,
            "AmmoPackChargeCnt": 1,
            "SceneAmmoBoxChargeCnt": 1,
            "bOnlyWeaponCountAmmo": true,
            "bRebornReset": true,
            "bPauseCanAddScore": true,
            "InitialChargingPercent": 0,
            "bChargingOnlyWhenEmpty": false
          },
          {
            "_StructType": "FStructFallback",
            "Init": 2,
            "Max": 2,
            "Time": 45,
            "UseTime": 0,
            "ChargeAmmoReplenish": 1,
            "PerkScaleMap": [],
            "MaxScoreReduceCDPercent": 0.25,
            "MaxScore": 0,
            "LimitPlayMode": [
              "EDFMGamePlayMode::GamePlayMode_BombDefusal"
            ],
            "LimitPlaySubMode": [],
            "AddToCurrentAmmo": false,
            "CurrentAmmoNum": 0,
            "MaxClipAmmoNum": 0,
            "SkillNumType": "ESkillNumType::UT_Item",
            "DoneVoiceString": "",
            "NoCDType": false,
            "bWeaponCheckAmmo": false,
            "bUseLocalAmmo": false,
            "AmmoBoxChargeCnt": 0,
            "AmmoPackChargeCnt": 0,
            "SceneAmmoBoxChargeCnt": 0,
            "bOnlyWeaponCountAmmo": true,
            "bRebornReset": true,
            "bPauseCanAddScore": true,
            "InitialChargingPercent": 0,
            "bChargingOnlyWhenEmpty": false
          },
          {
            "_StructType": "FStructFallback",
            "Init": 2,
            "Max": 2,
            "Time": 45,
            "UseTime": 0,
            "ChargeAmmoReplenish": 1,
            "PerkScaleMap": [],
            "MaxScoreReduceCDPercent": 0.25,
            "MaxScore": 0,
            "LimitPlayMode": [
              "EDFMGamePlayMode::GamePlayMode_GoldenGunGun"
            ],
            "LimitPlaySubMode": [],
            "AddToCurrentAmmo": false,
            "CurrentAmmoNum": 0,
            "MaxClipAmmoNum": 0,
            "SkillNumType": "ESkillNumType::UT_Item",
            "DoneVoiceString": "",
            "NoCDType": false,
            "bWeaponCheckAmmo": false,
            "bUseLocalAmmo": false,
            "AmmoBoxChargeCnt": 0,
            "AmmoPackChargeCnt": 0,
            "SceneAmmoBoxChargeCnt": 0,
            "bOnlyWeaponCountAmmo": true,
            "bRebornReset": true,
            "bPauseCanAddScore": true,
            "InitialChargingPercent": 0,
            "bChargingOnlyWhenEmpty": false
          }
        ],
        "CheckSubMode": false,
        "RowDescription": "None"
      },
      "\u58F0\u6CE2\u63A2\u6D4B\u88C5\u7F6E": {
        "CdID": 83,
        "Slot": "ECharingSlot::Ability",
        "WeaponSlot": 0,
        "SlotChargingData": [
          {
            "_StructType": "FStructFallback",
            "Init": 0,
            "Max": 1,
            "Time": 90,
            "UseTime": 0,
            "ChargeAmmoReplenish": 1,
            "PerkScaleMap": [],
            "MaxScoreReduceCDPercent": 0.25,
            "MaxScore": 0,
            "LimitPlayMode": [
              "EDFMGamePlayMode::GamePlayMode_SOL",
              "EDFMGamePlayMode::GamePlayMode_Raid",
              "EDFMGamePlayMode::GamePlayMode_Intro",
              "EDFMGamePlayMode::GamePlayMode_SafeHouse",
              "EDFMGamePlayMode::GamePlayMode_IrisDiscovery"
            ],
            "LimitPlaySubMode": [],
            "AddToCurrentAmmo": false,
            "CurrentAmmoNum": 0,
            "MaxClipAmmoNum": 0,
            "SkillNumType": "ESkillNumType::UT_NoShow",
            "DoneVoiceString": "Skill_Ultimate_Charged",
            "NoCDType": false,
            "bWeaponCheckAmmo": false,
            "bUseLocalAmmo": false,
            "AmmoBoxChargeCnt": 0,
            "AmmoPackChargeCnt": 0,
            "SceneAmmoBoxChargeCnt": 0,
            "bOnlyWeaponCountAmmo": true,
            "bRebornReset": false,
            "bPauseCanAddScore": true,
            "InitialChargingPercent": 0,
            "bChargingOnlyWhenEmpty": false
          },
          {
            "_StructType": "FStructFallback",
            "Init": 0,
            "Max": 1,
            "Time": 75,
            "UseTime": 0,
            "ChargeAmmoReplenish": 1,
            "PerkScaleMap": [],
            "MaxScoreReduceCDPercent": 0.25,
            "MaxScore": 13500,
            "LimitPlayMode": [
              "EDFMGamePlayMode::GamePlayMode_Breakthrough",
              "EDFMGamePlayMode::GamePlayMode_Conquest"
            ],
            "LimitPlaySubMode": [],
            "AddToCurrentAmmo": false,
            "CurrentAmmoNum": 0,
            "MaxClipAmmoNum": 0,
            "SkillNumType": "ESkillNumType::UT_NoShow",
            "DoneVoiceString": "",
            "NoCDType": false,
            "bWeaponCheckAmmo": false,
            "bUseLocalAmmo": false,
            "AmmoBoxChargeCnt": 0,
            "AmmoPackChargeCnt": 0,
            "SceneAmmoBoxChargeCnt": 0,
            "bOnlyWeaponCountAmmo": true,
            "bRebornReset": false,
            "bPauseCanAddScore": true,
            "InitialChargingPercent": 0,
            "bChargingOnlyWhenEmpty": false
          },
          {
            "_StructType": "FStructFallback",
            "Init": 0,
            "Max": 1,
            "Time": 90,
            "UseTime": 0,
            "ChargeAmmoReplenish": 1,
            "PerkScaleMap": [],
            "MaxScoreReduceCDPercent": 0.25,
            "MaxScore": 0,
            "LimitPlayMode": [],
            "LimitPlaySubMode": [
              "EDFMGamePlaySubMode::GamePlaySubMode_Arena"
            ],
            "AddToCurrentAmmo": true,
            "CurrentAmmoNum": 0,
            "MaxClipAmmoNum": 0,
            "SkillNumType": "ESkillNumType::UT_NoShow",
            "DoneVoiceString": "Skill_Ultimate_Charged",
            "NoCDType": false,
            "bWeaponCheckAmmo": false,
            "bUseLocalAmmo": false,
            "AmmoBoxChargeCnt": 0,
            "AmmoPackChargeCnt": 0,
            "SceneAmmoBoxChargeCnt": 0,
            "bOnlyWeaponCountAmmo": true,
            "bRebornReset": true,
            "bPauseCanAddScore": true,
            "InitialChargingPercent": 0,
            "bChargingOnlyWhenEmpty": false
          },
          {
            "_StructType": "FStructFallback",
            "Init": 0,
            "Max": 1,
            "Time": 75,
            "UseTime": 0,
            "ChargeAmmoReplenish": 1,
            "PerkScaleMap": [],
            "MaxScoreReduceCDPercent": 0.25,
            "MaxScore": 13500,
            "LimitPlayMode": [],
            "LimitPlaySubMode": [
              "EDFMGamePlaySubMode::GamePlaySubMode_TacticalConquest",
              "EDFMGamePlaySubMode::GamePlaySubMode_CaptureFlag"
            ],
            "AddToCurrentAmmo": true,
            "CurrentAmmoNum": 0,
            "MaxClipAmmoNum": 0,
            "SkillNumType": "ESkillNumType::UT_NoShow",
            "DoneVoiceString": "",
            "NoCDType": false,
            "bWeaponCheckAmmo": false,
            "bUseLocalAmmo": false,
            "AmmoBoxChargeCnt": 0,
            "AmmoPackChargeCnt": 0,
            "SceneAmmoBoxChargeCnt": 0,
            "bOnlyWeaponCountAmmo": true,
            "bRebornReset": false,
            "bPauseCanAddScore": true,
            "InitialChargingPercent": 0,
            "bChargingOnlyWhenEmpty": false
          },
          {
            "_StructType": "FStructFallback",
            "Init": 0,
            "Max": 1,
            "Time": 90,
            "UseTime": 0,
            "ChargeAmmoReplenish": 1,
            "PerkScaleMap": [],
            "MaxScoreReduceCDPercent": 0.25,
            "MaxScore": 0,
            "LimitPlayMode": [
              "EDFMGamePlayMode::GamePlayMode_BombDefusal"
            ],
            "LimitPlaySubMode": [],
            "AddToCurrentAmmo": false,
            "CurrentAmmoNum": 0,
            "MaxClipAmmoNum": 0,
            "SkillNumType": "ESkillNumType::UT_NoShow",
            "DoneVoiceString": "UltimateFullyCharged401",
            "NoCDType": false,
            "bWeaponCheckAmmo": false,
            "bUseLocalAmmo": false,
            "AmmoBoxChargeCnt": 0,
            "AmmoPackChargeCnt": 0,
            "SceneAmmoBoxChargeCnt": 0,
            "bOnlyWeaponCountAmmo": true,
            "bRebornReset": true,
            "bPauseCanAddScore": true,
            "InitialChargingPercent": 0,
            "bChargingOnlyWhenEmpty": false
          },
          {
            "_StructType": "FStructFallback",
            "Init": 0,
            "Max": 1,
            "Time": 90,
            "UseTime": 0,
            "ChargeAmmoReplenish": 1,
            "PerkScaleMap": [],
            "MaxScoreReduceCDPercent": 0.25,
            "MaxScore": 0,
            "LimitPlayMode": [
              "EDFMGamePlayMode::GamePlayMode_GoldenGunGun"
            ],
            "LimitPlaySubMode": [],
            "AddToCurrentAmmo": false,
            "CurrentAmmoNum": 0,
            "MaxClipAmmoNum": 0,
            "SkillNumType": "ESkillNumType::UT_NoShow",
            "DoneVoiceString": "UltimateFullyCharged401",
            "NoCDType": false,
            "bWeaponCheckAmmo": false,
            "bUseLocalAmmo": false,
            "AmmoBoxChargeCnt": 0,
            "AmmoPackChargeCnt": 0,
            "SceneAmmoBoxChargeCnt": 0,
            "bOnlyWeaponCountAmmo": true,
            "bRebornReset": true,
            "bPauseCanAddScore": true,
            "InitialChargingPercent": 0,
            "bChargingOnlyWhenEmpty": false
          }
        ],
        "CheckSubMode": true,
        "RowDescription": "None"
      },
      "C405_V": {
        "CdID": 98,
        "Slot": "ECharingSlot::ArmdedForceItem1",
        "WeaponSlot": 0,
        "SlotChargingData": [
          {
            "_StructType": "FStructFallback",
            "Init": 2,
            "Max": 2,
            "Time": 35,
            "UseTime": 0,
            "ChargeAmmoReplenish": 1,
            "PerkScaleMap": [],
            "MaxScoreReduceCDPercent": 0.25,
            "MaxScore": 0,
            "LimitPlayMode": [
              "EDFMGamePlayMode::GamePlayMode_SOL",
              "EDFMGamePlayMode::GamePlayMode_Raid",
              "EDFMGamePlayMode::GamePlayMode_IrisDiscovery",
              "EDFMGamePlayMode::GamePlayMode_SafeHouse",
              "EDFMGamePlayMode::GamePlayMode_Intro"
            ],
            "LimitPlaySubMode": [],
            "AddToCurrentAmmo": false,
            "CurrentAmmoNum": 0,
            "MaxClipAmmoNum": 0,
            "SkillNumType": "ESkillNumType::UT_Item",
            "DoneVoiceString": "",
            "NoCDType": false,
            "bWeaponCheckAmmo": false,
            "bUseLocalAmmo": false,
            "AmmoBoxChargeCnt": 0,
            "AmmoPackChargeCnt": 0,
            "SceneAmmoBoxChargeCnt": 0,
            "bOnlyWeaponCountAmmo": true,
            "bRebornReset": true,
            "bPauseCanAddScore": true,
            "InitialChargingPercent": 0,
            "bChargingOnlyWhenEmpty": false
          },
          {
            "_StructType": "FStructFallback",
            "Init": 2,
            "Max": 2,
            "Time": 25,
            "UseTime": 0,
            "ChargeAmmoReplenish": 1,
            "PerkScaleMap": [],
            "MaxScoreReduceCDPercent": 0.25,
            "MaxScore": 0,
            "LimitPlayMode": [
              "EDFMGamePlayMode::GamePlayMode_Conquest",
              "EDFMGamePlayMode::GamePlayMode_Breakthrough"
            ],
            "LimitPlaySubMode": [],
            "AddToCurrentAmmo": false,
            "CurrentAmmoNum": 0,
            "MaxClipAmmoNum": 0,
            "SkillNumType": "ESkillNumType::UT_Item",
            "DoneVoiceString": "",
            "NoCDType": false,
            "bWeaponCheckAmmo": false,
            "bUseLocalAmmo": false,
            "AmmoBoxChargeCnt": 0,
            "AmmoPackChargeCnt": 0,
            "SceneAmmoBoxChargeCnt": 0,
            "bOnlyWeaponCountAmmo": true,
            "bRebornReset": true,
            "bPauseCanAddScore": true,
            "InitialChargingPercent": 0,
            "bChargingOnlyWhenEmpty": false
          }
        ],
        "CheckSubMode": false,
        "RowDescription": "None"
      },
      "C405_G": {
        "CdID": 99,
        "Slot": "ECharingSlot::ArmdedForceItem2",
        "WeaponSlot": 0,
        "SlotChargingData": [
          {
            "_StructType": "FStructFallback",
            "Init": 1,
            "Max": 1,
            "Time": 25,
            "UseTime": 0,
            "ChargeAmmoReplenish": 1,
            "PerkScaleMap": [],
            "MaxScoreReduceCDPercent": 0.25,
            "MaxScore": 0,
            "LimitPlayMode": [
              "EDFMGamePlayMode::GamePlayMode_SOL",
              "EDFMGamePlayMode::GamePlayMode_Raid",
              "EDFMGamePlayMode::GamePlayMode_IrisDiscovery",
              "EDFMGamePlayMode::GamePlayMode_SafeHouse",
              "EDFMGamePlayMode::GamePlayMode_Intro"
            ],
            "LimitPlaySubMode": [],
            "AddToCurrentAmmo": false,
            "CurrentAmmoNum": 0,
            "MaxClipAmmoNum": 0,
            "SkillNumType": "ESkillNumType::UT_Item",
            "DoneVoiceString": "",
            "NoCDType": false,
            "bWeaponCheckAmmo": false,
            "bUseLocalAmmo": false,
            "AmmoBoxChargeCnt": 0,
            "AmmoPackChargeCnt": 0,
            "SceneAmmoBoxChargeCnt": 0,
            "bOnlyWeaponCountAmmo": true,
            "bRebornReset": true,
            "bPauseCanAddScore": true,
            "InitialChargingPercent": 0,
            "bChargingOnlyWhenEmpty": false
          },
          {
            "_StructType": "FStructFallback",
            "Init": 2,
            "Max": 2,
            "Time": 25,
            "UseTime": 0,
            "ChargeAmmoReplenish": 1,
            "PerkScaleMap": [],
            "MaxScoreReduceCDPercent": 0.25,
            "MaxScore": 0,
            "LimitPlayMode": [
              "EDFMGamePlayMode::GamePlayMode_Conquest",
              "EDFMGamePlayMode::GamePlayMode_Breakthrough"
            ],
            "LimitPlaySubMode": [],
            "AddToCurrentAmmo": false,
            "CurrentAmmoNum": 0,
            "MaxClipAmmoNum": 0,
            "SkillNumType": "ESkillNumType::UT_Item",
            "DoneVoiceString": "",
            "NoCDType": false,
            "bWeaponCheckAmmo": false,
            "bUseLocalAmmo": false,
            "AmmoBoxChargeCnt": 0,
            "AmmoPackChargeCnt": 0,
            "SceneAmmoBoxChargeCnt": 0,
            "bOnlyWeaponCountAmmo": true,
            "bRebornReset": true,
            "bPauseCanAddScore": true,
            "InitialChargingPercent": 0,
            "bChargingOnlyWhenEmpty": false
          }
        ],
        "CheckSubMode": false,
        "RowDescription": "None"
      },
      "C405_X": {
        "CdID": 100,
        "Slot": "ECharingSlot::Ability",
        "WeaponSlot": 134,
        "SlotChargingData": [
          {
            "_StructType": "FStructFallback",
            "Init": 0,
            "Max": 0,
            "Time": 100,
            "UseTime": 0,
            "ChargeAmmoReplenish": 6,
            "PerkScaleMap": [],
            "MaxScoreReduceCDPercent": 0.25,
            "MaxScore": 0,
            "LimitPlayMode": [
              "EDFMGamePlayMode::GamePlayMode_SOL",
              "EDFMGamePlayMode::GamePlayMode_Raid",
              "EDFMGamePlayMode::GamePlayMode_IrisDiscovery",
              "EDFMGamePlayMode::GamePlayMode_SafeHouse",
              "EDFMGamePlayMode::GamePlayMode_Intro"
            ],
            "LimitPlaySubMode": [],
            "AddToCurrentAmmo": true,
            "CurrentAmmoNum": 6,
            "MaxClipAmmoNum": 6,
            "SkillNumType": "ESkillNumType::UT_Item",
            "DoneVoiceString": "",
            "NoCDType": false,
            "bWeaponCheckAmmo": false,
            "bUseLocalAmmo": false,
            "AmmoBoxChargeCnt": 0,
            "AmmoPackChargeCnt": 0,
            "SceneAmmoBoxChargeCnt": 0,
            "bOnlyWeaponCountAmmo": true,
            "bRebornReset": true,
            "bPauseCanAddScore": true,
            "InitialChargingPercent": 0,
            "bChargingOnlyWhenEmpty": true
          },
          {
            "_StructType": "FStructFallback",
            "Init": 0,
            "Max": 0,
            "Time": 25,
            "UseTime": 0,
            "ChargeAmmoReplenish": 6,
            "PerkScaleMap": [],
            "MaxScoreReduceCDPercent": 0.25,
            "MaxScore": 0,
            "LimitPlayMode": [
              "EDFMGamePlayMode::GamePlayMode_Conquest",
              "EDFMGamePlayMode::GamePlayMode_Breakthrough"
            ],
            "LimitPlaySubMode": [],
            "AddToCurrentAmmo": true,
            "CurrentAmmoNum": 6,
            "MaxClipAmmoNum": 6,
            "SkillNumType": "ESkillNumType::UT_Item",
            "DoneVoiceString": "",
            "NoCDType": false,
            "bWeaponCheckAmmo": false,
            "bUseLocalAmmo": false,
            "AmmoBoxChargeCnt": 0,
            "AmmoPackChargeCnt": 0,
            "SceneAmmoBoxChargeCnt": 0,
            "bOnlyWeaponCountAmmo": true,
            "bRebornReset": true,
            "bPauseCanAddScore": true,
            "InitialChargingPercent": 0,
            "bChargingOnlyWhenEmpty": true
          }
        ],
        "CheckSubMode": false,
        "RowDescription": "None"
      }
    },
    "_RowCount": 12
  }
]